chapisha/__init__.py
chapisha/__main__.py
chapisha/create/__init__.py
chapisha/create/create.py
chapisha/helpers/__init__.py
chapisha/helpers/coreio.py
chapisha/helpers/data/css/core.css
chapisha/helpers/data/fonts/PT-Sans-Bold.ttf
chapisha/helpers/data/fonts/PT-Sans-Italic.ttf
chapisha/helpers/data/fonts/PT-Sans.ttf
chapisha/helpers/data/fonts/PT-Serif-Bold.ttf
chapisha/helpers/data/fonts/PT-Serif-Italic.ttf
chapisha/helpers/data/fonts/PT-Serif.ttf
chapisha/helpers/data/images/logo.svg
chapisha/helpers/data/images/titlepage.svg
chapisha/helpers/data/xhtml/chapter-template.xhtml
chapisha/helpers/data/xhtml/colophon.xhtml
chapisha/helpers/data/xhtml/container.xml
chapisha/helpers/data/xhtml/content.opf
chapisha/helpers/data/xhtml/dedication.xhtml
chapisha/helpers/data/xhtml/mimetype
chapisha/helpers/data/xhtml/onix.xml
chapisha/helpers/data/xhtml/titlepage.xhtml
chapisha/helpers/data/xhtml/toc.ncx
chapisha/helpers/data/xhtml/toc.xhtml
chapisha/helpers/formats.py
chapisha/helpers/pages.py
chapisha/helpers/updatezipfile.py
chapisha/models/__init__.py
chapisha/models/matter.py
chapisha/models/metadata.py
chapisha/review/__init__.py
chapisha/review/review.py
tests/data/cover.jpg
tests/data/usan-abasis-lament.docx
tests/data/usan-abasis-lament.odt
chapisha-0.6.0.dist-info/LICENSE
chapisha-0.6.0.dist-info/METADATA
chapisha-0.6.0.dist-info/WHEEL
chapisha-0.6.0.dist-info/RECORD
