Metadata-Version: 2.1
Name: chapisha
Version: 0.6.0
Summary: Chapisha: docx to standards-compliant epub3 conversion
Home-page: https://github.com/whythawk/chapisha
License: BSD-3-Clause
Keywords: python3,epub-generation,epub3,docx-to-epub
Author: Gavin Chait
Author-email: gchait@whythawk.com
Requires-Python: >=3.12,<4.0
Classifier: License :: OSI Approved :: BSD License
Classifier: Programming Language :: Python :: 3
Classifier: Programming Language :: Python :: 3.12
Classifier: Topic :: Text Processing
Classifier: Topic :: Text Processing :: General
Provides-Extra: docs
Requires-Dist: Pillow (>=10.3.0,<11.0.0)
Requires-Dist: beautifulsoup4 (>=4.12.3,<5.0.0)
Requires-Dist: epubcheck (>=4.2.6,<5.0.0)
Requires-Dist: filetype (>=1.2.0,<2.0.0)
Requires-Dist: lxml (>=5.2.2,<6.0.0)
Requires-Dist: pydantic (>=2.7.1,<3.0.0)
Requires-Dist: pypandoc (>=1.13,<2.0)
Requires-Dist: regex (>=2024.5.10,<2025.0.0)
Requires-Dist: tomlkit (>=0.12.5,<0.13.0)
Project-URL: Documentation, https://chapisha.readthedocs.io/
Project-URL: Repository, https://github.com/whythawk/chapisha
